bungieapi/__init__.py
bungieapi/base.py
bungieapi/certs/localhost-key.pem
bungieapi/certs/localhost.pem
bungieapi/client.py
bungieapi/forge.py
bungieapi/generated/__init__.py
bungieapi/generated/clients/__init__.py
bungieapi/generated/clients/app.py
bungieapi/generated/clients/community_content.py
bungieapi/generated/clients/content.py
bungieapi/generated/clients/destiny2.py
bungieapi/generated/clients/fireteam.py
bungieapi/generated/clients/forum.py
bungieapi/generated/clients/group_v2.py
bungieapi/generated/clients/root.py
bungieapi/generated/clients/social.py
bungieapi/generated/clients/tokens.py
bungieapi/generated/clients/trending.py
bungieapi/generated/clients/user.py
bungieapi/generated/components/__init__.py
bungieapi/generated/components/responses/__init__.py
bungieapi/generated/components/responses/applications.py
bungieapi/generated/components/responses/common/__init__.py
bungieapi/generated/components/responses/common/models.py
bungieapi/generated/components/responses/config/__init__.py
bungieapi/generated/components/responses/config/clan_banner.py
bungieapi/generated/components/responses/content/__init__.py
bungieapi/generated/components/responses/content/models.py
bungieapi/generated/components/responses/destiny/__init__.py
bungieapi/generated/components/responses/destiny/advanced.py
bungieapi/generated/components/responses/destiny/config.py
bungieapi/generated/components/responses/destiny/definitions.py
bungieapi/generated/components/responses/destiny/historical_stats.py
bungieapi/generated/components/responses/destiny/milestones.py
bungieapi/generated/components/responses/destiny/responses.py
bungieapi/generated/components/responses/fireteam.py
bungieapi/generated/components/responses/forum.py
bungieapi/generated/components/responses/groups_v2.py
bungieapi/generated/components/responses/social/__init__.py
bungieapi/generated/components/responses/social/friends.py
bungieapi/generated/components/responses/trending.py
bungieapi-0.0.5.dist-info/WHEEL
bungieapi-0.0.5.dist-info/METADATA
bungieapi-0.0.5.dist-info/RECORD
