Metadata-Version: 2.1
Name: bungieapi
Version: 0.0.5
Summary: Python client for bungie api
Author: Damian Świstowski
Author-email: damian@swistowski.org
Requires-Python: >=3.10,<4.0
Classifier: Programming Language :: Python :: 3
Classifier: Programming Language :: Python :: 3.10
Requires-Dist: aiohttp (>=3.8.1,<4.0.0)
Requires-Dist: svarog (>=0.2.2,<0.3.0)
